<?xml version="1.0" encoding="UTF-8"?>
<result>
<query id="60483">:facetid:toc:\"db/conf/vldb/vldb2000.bht\"</query>
<status code="200">OK</status>
<time unit="msecs">87.32</time>
<completions total="1" computed="1" sent="1">
<c sc="97" dc="97" oc="97" id="46512185">:facetid:toc:db/conf/vldb/vldb2000.bht</c>
</completions>
<hits total="97" computed="97" sent="97" first="0">
<hit score="1" id="6945747">
<info><authors><author pid="65/1481">Asaf Adi</author><author pid="27/6689">David Botzer</author><author pid="e/OEtzion">Opher Etzion</author><author pid="88/1057">Tali Yatzkar-Haham</author></authors><title>Push Technology Personalization through Event Correlation.</title><venue>VLDB</venue><pages>643-645</pages><year>2000</year><type>Conference and Workshop Papers</type><access>open</access><key>conf/vldb/AdiBEY00</key><ee>http://www.vldb.org/conf/2000/P643.pdf</ee><url>https://dblp.org/rec/conf/vldb/AdiBEY00</url></info>
<url>URL#6945747</url>
</hit>
<hit score="1" id="6945748">
<info><authors><author pid="a/SanjayAgrawal">Sanjay Agrawal 0001</author><author pid="c/SurajitChaudhuri">Surajit Chaudhuri</author><author pid="n/VivekRNarasayya">Vivek R. Narasayya</author></authors><title>Automated Selection of Materialized Views and Indexes in SQL Databases.</title><venue>VLDB</venue><pages>496-505</pages><year>2000</year><type>Conference and Workshop Papers</type><access>open</access><key>conf/vldb/AgrawalCN00</key><ee>http://www.vldb.org/conf/2000/P496.pdf</ee><url>https://dblp.org/rec/conf/vldb/AgrawalCN00</url></info>
<url>URL#6945748</url>
</hit>
<hit score="1" id="6945749">
<info><authors><author pid="02/6597">Mehmet Altinel</author><author pid="f/MJFranklin">Michael J. Franklin</author></authors><title>Efficient Filtering of XML Documents for Selective Dissemination of Information.</title><venue>VLDB</venue><pages>53-64</pages><year>2000</year><type>Conference and Workshop Papers</type><access>open</access><key>conf/vldb/AltinelF00</key><ee>http://www.vldb.org/conf/2000/P053.pdf</ee><url>https://dblp.org/rec/conf/vldb/AltinelF00</url></info>
<url>URL#6945749</url>
</hit>
<hit score="1" id="6945750">
<info><authors><author pid="44/4147">Andrey Balmin</author><author pid="04/6543">Thanos Papadimitriou</author><author pid="p/YPapakonstantinou">Yannis Papakonstantinou</author></authors><title>Hypothetical Queries in an OLAP Environment.</title><venue>VLDB</venue><pages>220-231</pages><year>2000</year><type>Conference and Workshop Papers</type><access>open</access><key>conf/vldb/BalminPP00</key><ee>http://www.vldb.org/conf/2000/P220.pdf</ee><url>https://dblp.org/rec/conf/vldb/BalminPP00</url></info>
<url>URL#6945750</url>
</hit>
<hit score="1" id="6945751">
<info><authors><author pid="35/2869">Sandeepan Banerjee</author></authors><title>A Database Platform for Bioinformatics.</title><venue>VLDB</venue><pages>705-710</pages><year>2000</year><type>Conference and Workshop Papers</type><access>open</access><key>conf/vldb/Banerjee00</key><ee>http://www.vldb.org/conf/2000/P705.pdf</ee><url>https://dblp.org/rec/conf/vldb/Banerjee00</url></info>
<url>URL#6945751</url>
</hit>
<hit score="1" id="6945752">
<info><authors><author pid="10/898">Ziv Bar-Yossef</author><author pid="73/2348">Alexander C. Berg</author><author pid="c/SteveChien">Steve Chien</author><author pid="63/319">Jittat Fakcharoenphol</author><author pid="13/1700">Dror Weitz</author></authors><title>Approximating Aggregate Queries about Web Pages via Random Walks.</title><venue>VLDB</venue><pages>535-544</pages><year>2000</year><type>Conference and Workshop Papers</type><access>open</access><key>conf/vldb/Bar-YossefBCFW00</key><ee>http://www.vldb.org/conf/2000/P535.pdf</ee><url>https://dblp.org/rec/conf/vldb/Bar-YossefBCFW00</url></info>
<url>URL#6945752</url>
</hit>
<hit score="1" id="6945753">
<info><authors><author pid="44/4427">Julie Basu</author><author pid="15/3467">José Alberto Fernández</author><author pid="34/4619">Olga Peschansky</author></authors><title>Building Scalable Internet Applications with Oracle8i Server.</title><venue>VLDB</venue><pages>649</pages><year>2000</year><type>Conference and Workshop Papers</type><access>open</access><key>conf/vldb/BasuFP00</key><ee>http://www.vldb.org/conf/2000/P649.pdf</ee><url>https://dblp.org/rec/conf/vldb/BasuFP00</url></info>
<url>URL#6945753</url>
</hit>
<hit score="1" id="6945754">
<info><authors><author pid="b/DBeneventano">Domenico Beneventano</author><author pid="b/SBergamaschi">Sonia Bergamaschi</author><author pid="c/SilvanaCastano">Silvana Castano</author><author pid="46/1143">Alberto Corni</author><author pid="23/5673">R. Guidetti</author><author pid="60/2952">G. Malvezzi</author><author pid="45/1072">Michele Melchiori</author><author pid="65/4364">Maurizio Vincini</author></authors><title>Information Integration: The MOMIS Project Demonstration.</title><venue>VLDB</venue><pages>611-614</pages><year>2000</year><type>Conference and Workshop Papers</type><access>open</access><key>conf/vldb/BeneventanoBCCGMMV00</key><ee>http://www.vldb.org/conf/2000/P611.pdf</ee><url>https://dblp.org/rec/conf/vldb/BeneventanoBCCGMMV00</url></info>
<url>URL#6945754</url>
</hit>
<hit score="1" id="6945755">
<info><authors><author pid="b/PhilipABernstein">Philip A. Bernstein</author><author pid="h/LauraMHaas">Laura M. Haas</author><author pid="j/MatthiasJarke">Matthias Jarke</author><author pid="r/ERahm">Erhard Rahm</author><author pid="w/GioWiederhold">Gio Wiederhold</author></authors><title>Panel: Is Generic Metadata Management Feasible?</title><venue>VLDB</venue><pages>660-662</pages><year>2000</year><type>Conference and Workshop Papers</type><access>open</access><key>conf/vldb/BernsteinHJRW00</key><ee>http://www.vldb.org/conf/2000/P660.pdf</ee><url>https://dblp.org/rec/conf/vldb/BernsteinHJRW00</url></info>
<url>URL#6945755</url>
</hit>
<hit score="1" id="6945756">
<info><authors><author pid="27/4393">Carsten Blecken</author></authors><title>Media360 Workflow-Implementing a Workflow Engine Inside a Database.</title><venue>VLDB</venue><pages>692</pages><year>2000</year><type>Conference and Workshop Papers</type><access>open</access><key>conf/vldb/Blecken00</key><ee>http://www.vldb.org/conf/2000/P692.pdf</ee><url>https://dblp.org/rec/conf/vldb/Blecken00</url></info>
<url>URL#6945756</url>
</hit>
<hit score="1" id="6945757">
<info><authors><author pid="75/1964">Geoffrey C. Bowker</author></authors><title>Work and Information Practices in the Sciences of Biodiversity.</title><venue>VLDB</venue><pages>693-696</pages><year>2000</year><type>Conference and Workshop Papers</type><access>open</access><key>conf/vldb/Bowker00</key><ee>http://www.vldb.org/conf/2000/P693.pdf</ee><url>https://dblp.org/rec/conf/vldb/Bowker00</url></info>
<url>URL#6945757</url>
</hit>
<hit score="1" id="6945758">
<info><authors><author pid="95/3763">Michael L. Brodie</author></authors><title>Panel: Future Directions of Database Research - The VLDB Broadening Strategy, Part 2.</title><venue>VLDB</venue><pages>665-672</pages><year>2000</year><type>Conference and Workshop Papers</type><access>open</access><key>conf/vldb/Brodie00</key><ee>http://www.vldb.org/conf/2000/P665.pdf</ee><url>https://dblp.org/rec/conf/vldb/Brodie00</url></info>
<url>URL#6945758</url>
</hit>
<hit score="1" id="6945759">
<info><authors><author pid="31/3455">Michael J. Carey 0001</author></authors><title>Toto, We&apos;re Not in Kansas Anymore: On Transitioning from Research to the Real (Invited Industrial Talk).</title><venue>VLDB</venue><pages>733</pages><year>2000</year><type>Conference and Workshop Papers</type><access>open</access><key>conf/vldb/Carey00</key><ee>http://www.vldb.org/conf/2000/P733.pdf</ee><url>https://dblp.org/rec/conf/vldb/Carey00</url></info>
<url>URL#6945759</url>
</hit>
<hit score="1" id="6945760">
<info><authors><author pid="31/3455">Michael J. Carey 0001</author><author pid="k/JerryKiernan">Jerry Kiernan</author><author pid="s/JShanmugasundaram">Jayavel Shanmugasundaram</author><author pid="03/6706">Eugene J. Shekita</author><author pid="s/IyerNSubramanian">Subbu N. Subramanian</author></authors><title>XPERANTO: Middleware for Publishing Object-Relational Data as XML Documents.</title><venue>VLDB</venue><pages>646-648</pages><year>2000</year><type>Conference and Workshop Papers</type><access>open</access><key>conf/vldb/CareyKSSS00</key><ee>http://www.vldb.org/conf/2000/P646.pdf</ee><url>https://dblp.org/rec/conf/vldb/CareyKSSS00</url></info>
<url>URL#6945760</url>
</hit>
<hit score="1" id="6945761">
<info><authors><author pid="95/6379">Francesco Caruso</author><author pid="20/317">Munir Cochinwala</author><author pid="44/5422">Uma Ganapathy</author><author pid="13/233">Gail Lalk</author><author pid="28/1062">Paolo Missier</author></authors><title>Telcordia&apos;s Database Reconciliation and Data Quality Analysis Tool.</title><venue>VLDB</venue><pages>615-618</pages><year>2000</year><type>Conference and Workshop Papers</type><access>open</access><key>conf/vldb/CarusoCGLM00</key><ee>http://www.vldb.org/conf/2000/P615.pdf</ee><url>https://dblp.org/rec/conf/vldb/CarusoCGLM00</url></info>
<url>URL#6945761</url>
</hit>
<hit score="1" id="6945762">
<info><authors><author pid="c/FabioCasati">Fabio Casati</author><author pid="64/561">Ming-Chien Shan</author></authors><title>Process Automation as the Foundation for E-Business.</title><venue>VLDB</venue><pages>688-691</pages><year>2000</year><type>Conference and Workshop Papers</type><access>open</access><key>conf/vldb/CasatiS00</key><ee>http://www.vldb.org/conf/2000/P688.pdf</ee><url>https://dblp.org/rec/conf/vldb/CasatiS00</url></info>
<url>URL#6945762</url>
</hit>
<hit score="1" id="6945763">
<info><authors><author pid="c/StefanoCeri">Stefano Ceri</author><author pid="93/595">Roberta Cochrane</author><author pid="w/JenniferWidom">Jennifer Widom</author></authors><title>Practical Applications of Triggers and Constraints: Success and Lingering Issues (10-Year Award).</title><venue>VLDB</venue><pages>254-262</pages><year>2000</year><type>Conference and Workshop Papers</type><access>open</access><key>conf/vldb/CeriCW00</key><ee>http://www.vldb.org/conf/2000/P254.pdf</ee><url>https://dblp.org/rec/conf/vldb/CeriCW00</url></info>
<url>URL#6945763</url>
</hit>
<hit score="1" id="6945764">
<info><authors><author pid="c/KaushikChakrabarti">Kaushik Chakrabarti</author><author pid="g/MinosNGarofalakis">Minos N. Garofalakis</author><author pid="r/RajeevRastogi">Rajeev Rastogi</author><author pid="s/KyuseokShim">Kyuseok Shim</author></authors><title>Approximate Query Processing Using Wavelets.</title><venue>VLDB</venue><pages>111-122</pages><year>2000</year><type>Conference and Workshop Papers</type><access>open</access><key>conf/vldb/ChakrabartiGRS00</key><ee>http://www.vldb.org/conf/2000/P111.pdf</ee><url>https://dblp.org/rec/conf/vldb/ChakrabartiGRS00</url></info>
<url>URL#6945764</url>
</hit>
<hit score="1" id="6945765">
<info><authors><author pid="c/KaushikChakrabarti">Kaushik Chakrabarti</author><author pid="m/SharadMehrotra">Sharad Mehrotra</author></authors><title>Local Dimensionality Reduction: A New Approach to Indexing High Dimensional Spaces.</title><venue>VLDB</venue><pages>89-100</pages><year>2000</year><type>Conference and Workshop Papers</type><access>open</access><key>conf/vldb/ChakrabartiM00</key><ee>http://www.vldb.org/conf/2000/P089.pdf</ee><url>https://dblp.org/rec/conf/vldb/ChakrabartiM00</url></info>
<url>URL#6945765</url>
</hit>
<hit score="1" id="6945766">
<info><authors><author pid="c/SChakrabarti">Soumen Chakrabarti</author><author pid="90/1261">Sandeep Srivastava</author><author pid="98/4153">Mallela Subramanyam</author><author pid="17/2124">Mitul Tiwari</author></authors><title>Memex: A Browsing Assistant for Collaborative Archiving and Mining of Surf Trails.</title><venue>VLDB</venue><pages>603-606</pages><year>2000</year><type>Conference and Workshop Papers</type><access>open</access><key>conf/vldb/ChakrabartiSST00</key><ee>http://www.vldb.org/conf/2000/P603.pdf</ee><url>https://dblp.org/rec/conf/vldb/ChakrabartiSST00</url></info>
<url>URL#6945766</url>
</hit>
<hit score="1" id="6945767">
<info><authors><author pid="c/KCCChang">Kevin Chen-Chuan Chang</author><author pid="g/HGarciaMolina">Hector Garcia-Molina</author></authors><title>Approximate Query Translation Across Heterogeneous Information Sources.</title><venue>VLDB</venue><pages>566-577</pages><year>2000</year><type>Conference and Workshop Papers</type><access>open</access><key>conf/vldb/ChangG00</key><ee>http://www.vldb.org/conf/2000/P566.pdf</ee><url>https://dblp.org/rec/conf/vldb/ChangG00</url></info>
<url>URL#6945767</url>
</hit>
<hit score="1" id="6945768">
<info><authors><author pid="c/SurajitChaudhuri">Surajit Chaudhuri</author><author pid="w/GerhardWeikum">Gerhard Weikum</author></authors><title>Rethinking Database System Architecture: Towards a Self-Tuning RISC-Style Database System.</title><venue>VLDB</venue><pages>1-10</pages><year>2000</year><type>Conference and Workshop Papers</type><access>open</access><key>conf/vldb/ChaudhuriW00</key><ee>http://www.vldb.org/conf/2000/P001.pdf</ee><url>https://dblp.org/rec/conf/vldb/ChaudhuriW00</url></info>
<url>URL#6945768</url>
</hit>
<hit score="1" id="6945769">
<info><authors><author pid="76/4977">Junghoo Cho</author><author pid="g/HGarciaMolina">Hector Garcia-Molina</author></authors><title>The Evolution of the Web and Implications for an Incremental Crawler.</title><venue>VLDB</venue><pages>200-209</pages><year>2000</year><type>Conference and Workshop Papers</type><access>open</access><key>conf/vldb/ChoG00</key><ee>http://www.vldb.org/conf/2000/P200.pdf</ee><url>https://dblp.org/rec/conf/vldb/ChoG00</url></info>
<url>URL#6945769</url>
</hit>
<hit score="1" id="6945770">
<info><authors><author pid="77/4054">Sunil Choenni</author></authors><title>Design and Implementation of a Genetic-Based Algorithm for Data Mining.</title><venue>VLDB</venue><pages>33-42</pages><year>2000</year><type>Conference and Workshop Papers</type><access>open</access><key>conf/vldb/ChoenniV00</key><ee>http://www.vldb.org/conf/2000/P033.pdf</ee><url>https://dblp.org/rec/conf/vldb/ChoenniV00</url></info>
<url>URL#6945770</url>
</hit>
<hit score="1" id="6945771">
<info><authors><author pid="41/6161">Christophe Bobineau</author><author pid="b/LucBouganim">Luc Bouganim</author><author pid="p/PPucheral">Philippe Pucheral</author><author pid="v/PatrickValduriez">Patrick Valduriez</author></authors><title>PicoDMBS: Scaling Down Database Techniques for the Smartcard.</title><venue>VLDB</venue><pages>11-20</pages><year>2000</year><type>Conference and Workshop Papers</type><access>open</access><key>conf/vldb/ChristopheBPV00</key><ee>http://www.vldb.org/conf/2000/P011.pdf</ee><url>https://dblp.org/rec/conf/vldb/ChristopheBPV00</url></info>
<url>URL#6945771</url>
</hit>
<hit score="1" id="6945772">
<info><authors><author pid="10/724">Gladys A. Cotter</author><author pid="23/2661">Barbara T. Bauldock</author></authors><title>Biodiversity Informatics Infrastructure: An Information Commons for the Biodiversity Community.</title><venue>VLDB</venue><pages>701-704</pages><year>2000</year><type>Conference and Workshop Papers</type><access>open</access><key>conf/vldb/CotterB00</key><ee>http://www.vldb.org/conf/2000/P701.pdf</ee><url>https://dblp.org/rec/conf/vldb/CotterB00</url></info>
<url>URL#6945772</url>
</hit>
<hit score="1" id="6945773">
<info><authors><author pid="32/5507">Wes Cowley</author><author pid="89/6058">Dimitris Plexousakis</author></authors><title>Temporal Integrity Constraints with Indeterminacy.</title><venue>VLDB</venue><pages>441-450</pages><year>2000</year><type>Conference and Workshop Papers</type><access>open</access><key>conf/vldb/CowleyP00</key><ee>http://www.vldb.org/conf/2000/P441.pdf</ee><url>https://dblp.org/rec/conf/vldb/CowleyP00</url></info>
<url>URL#6945773</url>
</hit>
<hit score="1" id="6945774">
<info><authors><author pid="42/3495">S. Misbah Deen</author><author pid="55/603">Anant Jhingran</author><author pid="n/ShamkantBNavathe">Shamkant B. Navathe</author><author pid="n/ErichJNeuhold">Erich J. Neuhold</author><author pid="w/GioWiederhold">Gio Wiederhold</author></authors><title>A 20/20 Vision of the VLDB-2020?</title><venue>VLDB</venue><pages>655-659</pages><year>2000</year><type>Conference and Workshop Papers</type><access>open</access><key>conf/vldb/DeenJNNW00</key><ee>http://www.vldb.org/conf/2000/P655.pdf</ee><url>https://dblp.org/rec/conf/vldb/DeenJNNW00</url></info>
<url>URL#6945774</url>
</hit>
<hit score="1" id="6945775">
<info><authors><author pid="07/576">Anand Deshpande</author></authors><title>Linking Business to Deliver Value: A Data Management Challenge.</title><venue>VLDB</venue><pages>682-683</pages><year>2000</year><type>Conference and Workshop Papers</type><access>open</access><key>conf/vldb/Deshpande00</key><ee>http://www.vldb.org/conf/2000/P682.pdf</ee><url>https://dblp.org/rec/conf/vldb/Deshpande00</url></info>
<url>URL#6945775</url>
</hit>
<hit score="1" id="6945776">
<info><authors><author pid="d/YanleiDiao">Yanlei Diao</author><author pid="l/HongjunLu">Hongjun Lu</author><author pid="64/1361">Songting Chen</author><author pid="41/187">Zengping Tian</author></authors><title>Toward Learning Based Web Query Processing.</title><venue>VLDB</venue><pages>317-328</pages><year>2000</year><type>Conference and Workshop Papers</type><access>open</access><key>conf/vldb/DiaoLCT00</key><ee>http://www.vldb.org/conf/2000/P317.pdf</ee><url>https://dblp.org/rec/conf/vldb/DiaoLCT00</url></info>
<url>URL#6945776</url>
</hit>
<hit score="1" id="6945777">
<info><authors><author pid="11/5691">Michelangelo Diligenti</author><author pid="95/3849">Frans Coetzee</author><author pid="96/6643">Steve Lawrence</author><author pid="g/CLeeGiles">C. Lee Giles</author><author pid="g/MarcoGori">Marco Gori</author></authors><title>Focused Crawling Using Context Graphs.</title><venue>VLDB</venue><pages>527-534</pages><year>2000</year><type>Conference and Workshop Papers</type><access>open</access><key>conf/vldb/DiligentiCLGG00</key><ee>http://www.vldb.org/conf/2000/P527.pdf</ee><url>https://dblp.org/rec/conf/vldb/DiligentiCLGG00</url></info>
<url>URL#6945777</url>
</hit>
<hit score="1" id="6945778">
<info><authors><author pid="81/716">Junyan Ding</author><author pid="g/LuisGravano">Luis Gravano</author><author pid="s/NShivakumar">Narayanan Shivakumar</author></authors><title>Computing Geographical Scopes of Web Resources.</title><venue>VLDB</venue><pages>545-556</pages><year>2000</year><type>Conference and Workshop Papers</type><access>open</access><key>conf/vldb/DingGS00</key><ee>http://www.vldb.org/conf/2000/P545.pdf</ee><url>https://dblp.org/rec/conf/vldb/DingGS00</url></info>
<url>URL#6945778</url>
</hit>
<hit score="1" id="6945779">
<info><authors><author pid="58/1227">Kaushik Dutta</author><author pid="d/AnindyaDatta">Anindya Datta</author><author pid="84/5479">Debra E. VanderMeer</author><author pid="r/KrithiRamamritham">Krithi Ramamritham</author><author pid="85/3996">Helen M. Thomas</author></authors><title>Demonstration: Enabling Scalable Online Personalization on the Web.</title><venue>VLDB</venue><pages>631-634</pages><year>2000</year><type>Conference and Workshop Papers</type><access>open</access><key>conf/vldb/DuttaDMRT00</key><ee>http://www.vldb.org/conf/2000/P631.pdf</ee><url>https://dblp.org/rec/conf/vldb/DuttaDMRT00</url></info>
<url>URL#6945779</url>
</hit>
<hit score="1" id="6945780">
<info><authors><author pid="g/VenkateshGanti">Venkatesh Ganti</author><author pid="l/MongLiLee">Mong-Li Lee</author><author pid="r/RaghuRamakrishnan">Raghu Ramakrishnan 0001</author></authors><title>ICICLES: Self-Tuning Samples for Approximate Query Answering.</title><venue>VLDB</venue><pages>176-187</pages><year>2000</year><type>Conference and Workshop Papers</type><access>open</access><key>conf/vldb/GantiLR00</key><ee>http://www.vldb.org/conf/2000/P176.pdf</ee><url>https://dblp.org/rec/conf/vldb/GantiLR00</url></info>
<url>URL#6945780</url>
</hit>
<hit score="1" id="6945781">
<info><authors><author pid="g/JonathanGoldstein">Jonathan Goldstein</author><author pid="r/RaghuRamakrishnan">Raghu Ramakrishnan 0001</author></authors><title>Contrast Plots and P-Sphere Trees: Space vs. Time in Nearest Neighbour Searches.</title><venue>VLDB</venue><pages>429-440</pages><year>2000</year><type>Conference and Workshop Papers</type><access>open</access><key>conf/vldb/GoldsteinR00</key><ee>http://www.vldb.org/conf/2000/P429.pdf</ee><url>https://dblp.org/rec/conf/vldb/GoldsteinR00</url></info>
<url>URL#6945781</url>
</hit>
<hit score="1" id="6945782">
<info><authors><author pid="g/SGrumbach">Stéphane Grumbach</author><author pid="r/PRigaux">Philippe Rigaux</author><author pid="s/LucSegoufin">Luc Segoufin</author></authors><title>Manipulating Interpolated Data is Easier than You Thought.</title><venue>VLDB</venue><pages>156-165</pages><year>2000</year><type>Conference and Workshop Papers</type><access>open</access><key>conf/vldb/GrumbachRS00</key><ee>http://www.vldb.org/conf/2000/P156.pdf</ee><url>https://dblp.org/rec/conf/vldb/GrumbachRS00</url></info>
<url>URL#6945782</url>
</hit>
<hit score="1" id="6945783">
<info><authors><author pid="70/1042">Junmin Gu</author><author pid="p/TorbenBachPedersen">Torben Bach Pedersen</author><author pid="s/ArieShoshani">Arie Shoshani</author></authors><title>OLAP++: Powerful and Easy-to-Use Federations of OLAP and Object Databases.</title><venue>VLDB</venue><pages>599-602</pages><year>2000</year><type>Conference and Workshop Papers</type><access>open</access><key>conf/vldb/GuPS00</key><ee>http://www.vldb.org/conf/2000/P599.pdf</ee><url>https://dblp.org/rec/conf/vldb/GuPS00</url></info>
<url>URL#6945783</url>
</hit>
<hit score="1" id="6945784">
<info><authors><author pid="39/985">Ulrich Güntzer</author><author pid="b/WTBalke">Wolf-Tilo Balke</author><author pid="k/WKiessling">Werner Kießling</author></authors><title>Optimizing Multi-Feature Queries for Image Databases.</title><venue>VLDB</venue><pages>419-428</pages><year>2000</year><type>Conference and Workshop Papers</type><access>open</access><key>conf/vldb/GuntzerBK00</key><ee>http://www.vldb.org/conf/2000/P419.pdf</ee><url>https://dblp.org/rec/conf/vldb/GuntzerBK00</url></info>
<url>URL#6945784</url>
</hit>
<hit score="1" id="6945785">
<info><authors><author pid="h/AHelal">Abdelsalam Helal</author><author pid="80/6898">Hua Li</author></authors><title>Rainbow: Distributed Database System for Classroom Education and Experimental Research.</title><venue>VLDB</venue><pages>619-622</pages><year>2000</year><type>Conference and Workshop Papers</type><access>open</access><key>conf/vldb/HelalL00</key><ee>http://www.vldb.org/conf/2000/P619.pdf</ee><url>https://dblp.org/rec/conf/vldb/HelalL00</url></info>
<url>URL#6945785</url>
</hit>
<hit score="1" id="6945786">
<info><authors><author pid="37/2076">Alexander Hinneburg</author><author pid="a/CharuCAggarwal">Charu C. Aggarwal</author><author pid="k/DanielAKeim">Daniel A. Keim</author></authors><title>What Is the Nearest Neighbor in High Dimensional Spaces?</title><venue>VLDB</venue><pages>506-515</pages><year>2000</year><type>Conference and Workshop Papers</type><access>open</access><key>conf/vldb/HinneburgAK00</key><ee>http://www.vldb.org/conf/2000/P506.pdf</ee><url>https://dblp.org/rec/conf/vldb/HinneburgAK00</url></info>
<url>URL#6945786</url>
</hit>
<hit score="1" id="6945787">
<info><authors><author pid="h/SOHvasshovd">Svein-Olaf Hvasshovd</author><author pid="b/SEBratsberg">Svein Erik Bratsberg</author><author pid="t/OysteinTorbjornsen">Øystein Torbjørnsen</author></authors><title>An Ultra Highly Available DBMS.</title><venue>VLDB</venue><pages>673</pages><year>2000</year><type>Conference and Workshop Papers</type><access>open</access><key>conf/vldb/HvasshovdBT00</key><ee>http://www.vldb.org/conf/2000/P673.pdf</ee><url>https://dblp.org/rec/conf/vldb/HvasshovdBT00</url></info>
<url>URL#6945787</url>
</hit>
<hit score="1" id="6945788">
<info><authors><author pid="j/MatthiasJarke">Matthias Jarke</author><author pid="86/3911">Thomas List</author><author pid="93/2358">Jörg Köller</author></authors><title>The Challenge of Process Data Warehousing.</title><venue>VLDB</venue><pages>473-483</pages><year>2000</year><type>Conference and Workshop Papers</type><access>open</access><key>conf/vldb/JarkeKL00</key><ee>http://www.vldb.org/conf/2000/P473.pdf</ee><url>https://dblp.org/rec/conf/vldb/JarkeKL00</url></info>
<url>URL#6945788</url>
</hit>
<hit score="1" id="6945789">
<info><authors><author pid="44/483">Linan Jiang</author><author pid="s/BettySalzberg">Betty Salzberg</author><author pid="l/DavidBLomet">David B. Lomet</author><author pid="86/6434">Manuel Barrena García</author></authors><title>The BT-tree: A Branched and Temporal Access Method.</title><venue>VLDB</venue><pages>451-460</pages><year>2000</year><type>Conference and Workshop Papers</type><access>open</access><key>conf/vldb/JiangSLB00</key><ee>http://www.vldb.org/conf/2000/P451.pdf</ee><url>https://dblp.org/rec/conf/vldb/JiangSLB00</url></info>
<url>URL#6945789</url>
</hit>
<hit score="1" id="6945790">
<info><authors><author pid="a/SihemAmerYahia">Sihem Amer-Yahia</author><author pid="j/TheodoreJohnson">Theodore Johnson</author></authors><title>Optimizing Queries on Compressed Bitmaps.</title><venue>VLDB</venue><pages>329-338</pages><year>2000</year><type>Conference and Workshop Papers</type><access>open</access><key>conf/vldb/JohnsonA00</key><ee>http://www.vldb.org/conf/2000/P329.pdf</ee><url>https://dblp.org/rec/conf/vldb/JohnsonA00</url></info>
<url>URL#6945790</url>
</hit>
<hit score="1" id="6945791">
<info><authors><author pid="k/BettinaKemme">Bettina Kemme</author><author pid="a/GustavoAlonso">Gustavo Alonso</author></authors><title>Don&apos;t Be Lazy, Be Consistent: Postgres-R, A New Way to Implement Database Replication.</title><venue>VLDB</venue><pages>134-143</pages><year>2000</year><type>Conference and Workshop Papers</type><access>open</access><key>conf/vldb/KemmeA00</key><ee>http://www.vldb.org/conf/2000/P134.pdf</ee><url>https://dblp.org/rec/conf/vldb/KemmeA00</url></info>
<url>URL#6945791</url>
</hit>
<hit score="1" id="6945792">
<info><authors><author pid="i/PiotrIndyk">Piotr Indyk</author><author pid="k/NickKoudas">Nick Koudas</author><author pid="m/SMuthukrishnan">S. Muthukrishnan 0001</author></authors><title>Identifying Representative Trends in Massive Time Series Data Sets Using Sketches.</title><venue>VLDB</venue><pages>363-372</pages><year>2000</year><type>Conference and Workshop Papers</type><access>open</access><key>conf/vldb/KoudasIM00</key><ee>http://www.vldb.org/conf/2000/P363.pdf</ee><url>https://dblp.org/rec/conf/vldb/KoudasIM00</url></info>
<url>URL#6945792</url>
</hit>
<hit score="1" id="6945793">
<info><authors><author pid="k/HansPeterKriegel">Hans-Peter Kriegel</author><author pid="p/MarcoPotke">Marco Pötke</author><author pid="s/ThomasSeidl1">Thomas Seidl 0001</author></authors><title>Managing Intervals Efficiently in Object-Relational Databases.</title><venue>VLDB</venue><pages>407-418</pages><year>2000</year><type>Conference and Workshop Papers</type><access>open</access><key>conf/vldb/KriegelPS00</key><ee>http://www.vldb.org/conf/2000/P407.pdf</ee><url>https://dblp.org/rec/conf/vldb/KriegelPS00</url></info>
<url>URL#6945793</url>
</hit>
<hit score="1" id="6945794">
<info><authors><author pid="l/WilburtLabio">Wilburt Labio</author><author pid="y/JunYang1">Jun Yang 0001</author><author pid="06/3051">Yingwei Cui</author><author pid="g/HGarciaMolina">Hector Garcia-Molina</author><author pid="w/JenniferWidom">Jennifer Widom</author></authors><title>Performance Issues in Incremental Warehouse Maintenance.</title><venue>VLDB</venue><pages>461-472</pages><year>2000</year><type>Conference and Workshop Papers</type><access>open</access><key>conf/vldb/LabioYCGW00</key><ee>http://www.vldb.org/conf/2000/P461.pdf</ee><url>https://dblp.org/rec/conf/vldb/LabioYCGW00</url></info>
<url>URL#6945794</url>
</hit>
<hit score="1" id="6945795">
<info><authors><author pid="43/469">Dave Liles</author></authors><title>The Zero Latency Enterprise.</title><venue>VLDB</venue><pages>674-676</pages><year>2000</year><type>Conference and Workshop Papers</type><access>open</access><key>conf/vldb/Ladin00</key><ee>http://www.vldb.org/conf/2000/P674.pdf</ee><url>https://dblp.org/rec/conf/vldb/Ladin00</url></info>
<url>URL#6945795</url>
</hit>
<hit score="1" id="6945796">
<info><authors><author pid="j/TheodoreJohnson">Theodore Johnson</author><author pid="l/LVSLakshmanan">Laks V. S. Lakshmanan</author><author pid="n/RTNg">Raymond T. Ng</author></authors><title>The 3W Model and Algebra for Unified Data Mining.</title><venue>VLDB</venue><pages>21-32</pages><year>2000</year><type>Conference and Workshop Papers</type><access>open</access><key>conf/vldb/LakshmananJN00</key><ee>http://www.vldb.org/conf/2000/P021.pdf</ee><url>https://dblp.org/rec/conf/vldb/LakshmananJN00</url></info>
<url>URL#6945796</url>
</hit>
<hit score="1" id="6945797">
<info><authors><author pid="31/2099">Meridith A. Lane</author><author pid="22/5123">James L. Edwards</author><author pid="33/652">Ebbe Nielsen</author></authors><title>Biodiversity Informatics: The Challenge of Rapid Development, Large Databases, and Complex Data (Keynote).</title><venue>VLDB</venue><pages>729-732</pages><year>2000</year><type>Conference and Workshop Papers</type><access>open</access><key>conf/vldb/LaneEN00</key><ee>http://www.vldb.org/conf/2000/P729.pdf</ee><url>https://dblp.org/rec/conf/vldb/LaneEN00</url></info>
<url>URL#6945797</url>
</hit>
<hit score="1" id="6945798">
<info><authors><author pid="04/1907">Sin Yeung Lee</author><author pid="l/TokWangLing">Tok Wang Ling</author><author pid="32/2042">Hua-Gang Li</author></authors><title>Hierarchical Compact Cube for Range-Max Queries.</title><venue>VLDB</venue><pages>232-241</pages><year>2000</year><type>Conference and Workshop Papers</type><access>open</access><key>conf/vldb/LingLL00</key><ee>http://www.vldb.org/conf/2000/P232.pdf</ee><url>https://dblp.org/rec/conf/vldb/LingLL00</url></info>
<url>URL#6945798</url>
</hit>
<hit score="1" id="6945799">
<info><authors><author pid="l/HongjunLu">Hongjun Lu</author><author pid="28/374">Hongyan Liu</author></authors><title>Decision Tables: Scalable Classification Exploring RDBMS Capabilities.</title><venue>VLDB</venue><pages>373-384</pages><year>2000</year><type>Conference and Workshop Papers</type><access>open</access><key>conf/vldb/LuL00</key><ee>http://www.vldb.org/conf/2000/P373.pdf</ee><url>https://dblp.org/rec/conf/vldb/LuL00</url></info>
<url>URL#6945799</url>
</hit>
<hit score="1" id="6945800">
<info><authors><author pid="l/BertramLudascher">Bertram Ludäscher</author><author pid="g/AmarnathGupta">Amarnath Gupta</author><author pid="62/2221">Maryann E. Martone</author></authors><title>Model-Based Information Integration in a Neuroscience Mediator System.</title><venue>VLDB</venue><pages>639-642</pages><year>2000</year><type>Conference and Workshop Papers</type><access>open</access><key>conf/vldb/LudasaherGM00</key><ee>http://www.vldb.org/conf/2000/P639.pdf</ee><url>https://dblp.org/rec/conf/vldb/LudasaherGM00</url></info>
<url>URL#6945800</url>
</hit>
<hit score="1" id="6945801">
<info><authors><author pid="m/StefanManegold">Stefan Manegold</author><author pid="b/PeterABoncz">Peter A. Boncz</author><author pid="k/MartinLKersten">Martin L. Kersten</author></authors><title>What Happens During a Join? Dissecting CPU and Memory Optimization Effects.</title><venue>VLDB</venue><pages>339-350</pages><year>2000</year><type>Conference and Workshop Papers</type><access>open</access><key>conf/vldb/ManegoldBK00</key><ee>http://www.vldb.org/conf/2000/P339.pdf</ee><url>https://dblp.org/rec/conf/vldb/ManegoldBK00</url></info>
<url>URL#6945801</url>
</hit>
<hit score="1" id="6945802">
<info><authors><author pid="m/IoanaManolescu">Ioana Manolescu</author><author pid="70/3007">Daniela Florescu</author><author pid="k/DonaldKossmann">Donald Kossmann</author><author pid="02/4296">Florian Xhumari</author><author pid="o/DanOlteanu">Dan Olteanu</author></authors><title>Agora: Living with XML and Relational.</title><venue>VLDB</venue><pages>623-626</pages><year>2000</year><type>Conference and Workshop Papers</type><access>open</access><key>conf/vldb/ManolescuFKXO00</key><ee>http://www.vldb.org/conf/2000/P623.pdf</ee><url>https://dblp.org/rec/conf/vldb/ManolescuFKXO00</url></info>
<url>URL#6945802</url>
</hit>
<hit score="1" id="6945803">
<info><authors><author pid="m/YossiMatias">Yossi Matias</author><author pid="v/JeffreyScottVitter">Jeffrey Scott Vitter</author><author pid="w/MinWang">Min Wang 0001</author></authors><title>Dynamic Maintenance of Wavelet-Based Histograms.</title><venue>VLDB</venue><pages>101-110</pages><year>2000</year><type>Conference and Workshop Papers</type><access>open</access><key>conf/vldb/MatiasVW00</key><ee>http://www.vldb.org/conf/2000/P101.pdf</ee><url>https://dblp.org/rec/conf/vldb/MatiasVW00</url></info>
<url>URL#6945803</url>
</hit>
<hit score="1" id="6945804">
<info><authors><author pid="m/AOMendelzon">Alberto O. Mendelzon</author><author pid="58/6139">Alejandro A. Vaisman</author></authors><title>Temporal Queries in OLAP.</title><venue>VLDB</venue><pages>242-253</pages><year>2000</year><type>Conference and Workshop Papers</type><access>open</access><key>conf/vldb/MendelzonV00</key><ee>http://www.vldb.org/conf/2000/P242.pdf</ee><url>https://dblp.org/rec/conf/vldb/MendelzonV00</url></info>
<url>URL#6945804</url>
</hit>
<hit score="1" id="6945805">
<info><authors><author pid="m/RJMiller">Renée J. Miller</author><author pid="h/LauraMHaas">Laura M. Haas</author><author pid="56/451">Mauricio A. Hernández</author></authors><title>Schema Mapping as Query Discovery.</title><venue>VLDB</venue><pages>77-88</pages><year>2000</year><type>Conference and Workshop Papers</type><access>open</access><key>conf/vldb/MillerHH00</key><ee>http://www.vldb.org/conf/2000/P077.pdf</ee><url>https://dblp.org/rec/conf/vldb/MillerHH00</url></info>
<url>URL#6945805</url>
</hit>
<hit score="1" id="6945806">
<info><authors><author pid="m/CMohan">C. Mohan 0001</author><author pid="33/3527">Ron Barber</author><author pid="04/1667">S. Watts</author><author pid="50/1300">Amit Somani</author><author pid="44/3258">Markos Zaharioudakis</author></authors><title>Evolution of Groupware for Business Applications: A Database Perspective on Lotus Domino/Notes.</title><venue>VLDB</venue><pages>684-687</pages><year>2000</year><type>Conference and Workshop Papers</type><access>open</access><key>conf/vldb/MohanBWSZ00</key><ee>http://www.vldb.org/conf/2000/P684.pdf</ee><url>https://dblp.org/rec/conf/vldb/MohanBWSZ00</url></info>
<url>URL#6945806</url>
</hit>
<hit score="1" id="6945807">
<info><authors><author pid="70/6074">Amir Netz</author><author pid="c/SurajitChaudhuri">Surajit Chaudhuri</author><author pid="65/6367">Jeff Bernhardt</author><author pid="f/UsamaMFayyad">Usama M. Fayyad</author></authors><title>Integration of Data Mining with Database Technology.</title><venue>VLDB</venue><pages>719-722</pages><year>2000</year><type>Conference and Workshop Papers</type><access>open</access><key>conf/vldb/NetzCBF00</key><ee>http://www.vldb.org/conf/2000/P719.pdf</ee><url>https://dblp.org/rec/conf/vldb/NetzCBF00</url></info>
<url>URL#6945807</url>
</hit>
<hit score="1" id="6945808">
<info><authors><author pid="85/3087">Anil Nori</author></authors><title>Asera: Extranet Architecture for B2B Solutions.</title><venue>VLDB</venue><pages>681</pages><year>2000</year><type>Conference and Workshop Papers</type><access>open</access><key>conf/vldb/Nori00</key><ee>http://www.vldb.org/conf/2000/P681.pdf</ee><url>https://dblp.org/rec/conf/vldb/Nori00</url></info>
<url>URL#6945808</url>
</hit>
<hit score="1" id="6945809">
<info><authors><author pid="o/ChristopherOlston">Chris Olston</author><author pid="w/JenniferWidom">Jennifer Widom</author></authors><title>Offering a Precision-Performance Tradeoff for Aggregation Queries over Replicated Data.</title><venue>VLDB</venue><pages>144-155</pages><year>2000</year><type>Conference and Workshop Papers</type><access>open</access><key>conf/vldb/OlstonW00</key><ee>http://www.vldb.org/conf/2000/P144.pdf</ee><url>https://dblp.org/rec/conf/vldb/OlstonW00</url></info>
<url>URL#6945809</url>
</hit>
<hit score="1" id="6945810">
<info><authors><author pid="31/4106">Maurizio Panti</author><author pid="83/522">Luca Spalazzi</author><author pid="65/636">Alberto Giretti</author></authors><title>A Case-Based Approach to Information Integration.</title><venue>VLDB</venue><pages>557-565</pages><year>2000</year><type>Conference and Workshop Papers</type><access>open</access><key>conf/vldb/PantiSG00</key><ee>http://www.vldb.org/conf/2000/P557.pdf</ee><url>https://dblp.org/rec/conf/vldb/PantiSG00</url></info>
<url>URL#6945810</url>
</hit>
<hit score="1" id="6945811">
<info><authors><author pid="07/3891">Nikos Pappas</author><author pid="66/2056">Stavros Christodoulakis</author></authors><title>Design and Development of a Stream Service in a Heterogenous Client Environment.</title><venue>VLDB</venue><pages>578-589</pages><year>2000</year><type>Conference and Workshop Papers</type><access>open</access><key>conf/vldb/PappasC00</key><ee>http://www.vldb.org/conf/2000/P578.pdf</ee><url>https://dblp.org/rec/conf/vldb/PappasC00</url></info>
<url>URL#6945811</url>
</hit>
<hit score="1" id="6945812">
<info><authors><author pid="45/5762">Guy Pardon</author><author pid="a/GustavoAlonso">Gustavo Alonso</author></authors><title>CheeTah: a Lightweight Transaction Server for Plug-and-Play Internet Data Management.</title><venue>VLDB</venue><pages>210-219</pages><year>2000</year><type>Conference and Workshop Papers</type><access>open</access><key>conf/vldb/PardonA00</key><ee>http://www.vldb.org/conf/2000/P210.pdf</ee><url>https://dblp.org/rec/conf/vldb/PardonA00</url></info>
<url>URL#6945812</url>
</hit>
<hit score="1" id="6945813">
<info><authors><author pid="p/TorbenBachPedersen">Torben Bach Pedersen</author><author pid="j/ChristianSJensen">Christian S. Jensen</author><author pid="d/CEDyreson">Curtis E. Dyreson</author></authors><title>The TreeScape System: Reuse of Pre-Computed Aggregates over Irregular OLAP Hierarchies.</title><venue>VLDB</venue><pages>595-598</pages><year>2000</year><type>Conference and Workshop Papers</type><access>open</access><key>conf/vldb/PedersenJD00</key><ee>http://www.vldb.org/conf/2000/P595.pdf</ee><url>https://dblp.org/rec/conf/vldb/PedersenJD00</url></info>
<url>URL#6945813</url>
</hit>
<hit score="1" id="6945814">
<info><authors><author pid="51/1587-2">João Pereira 0002</author><author pid="72/6766">Françoise Fabret</author><author pid="l/FLlirbat">François Llirbat</author><author pid="26/6879">Radu Preotiuc-Pietro</author><author pid="r/KARoss">Kenneth A. Ross</author><author pid="s/DennisShasha">Dennis E. Shasha</author></authors><title>Publish/Subscribe on the Web at Extreme Speed.</title><venue>VLDB</venue><pages>627-630</pages><year>2000</year><type>Conference and Workshop Papers</type><access>open</access><key>conf/vldb/PereiraFLS00</key><ee>http://www.vldb.org/conf/2000/P627.pdf</ee><url>https://dblp.org/rec/conf/vldb/PereiraFLS00</url></info>
<url>URL#6945814</url>
</hit>
<hit score="1" id="6945815">
<info><authors><author pid="p/DieterPfoser">Dieter Pfoser</author><author pid="j/ChristianSJensen">Christian S. Jensen</author><author pid="t/YannisTheodoridis">Yannis Theodoridis</author></authors><title>Novel Approaches to the Indexing of Moving Object Trajectories.</title><venue>VLDB</venue><pages>395-406</pages><year>2000</year><type>Conference and Workshop Papers</type><access>open</access><key>conf/vldb/PfoserJT00</key><ee>http://www.vldb.org/conf/2000/P395.pdf</ee><url>https://dblp.org/rec/conf/vldb/PfoserJT00</url></info>
<url>URL#6945815</url>
</hit>
<hit score="1" id="6945816">
<info><authors><author pid="68/1297">Rachel Pottinger</author><author pid="h/AlonYHalevy">Alon Y. Levy</author></authors><title>A Scalable Algorithm for Answering Queries Using Views.</title><venue>VLDB</venue><pages>484-495</pages><year>2000</year><type>Conference and Workshop Papers</type><access>open</access><key>conf/vldb/PottingerL00</key><ee>http://www.vldb.org/conf/2000/P484.pdf</ee><url>https://dblp.org/rec/conf/vldb/PottingerL00</url></info>
<url>URL#6945816</url>
</hit>
<hit score="1" id="6945817">
<info><authors><author pid="r/KrithiRamamritham">Krithi Ramamritham</author><author pid="30/6438">Yeha El Atfi</author><author pid="69/1334">Carlo Batini</author><author pid="16/333">Michael Eitan</author><author pid="58/1291">Valerie Gregg</author><author pid="p/DBPhatak">Deepak B. Phatak</author></authors><title>Social, Educational, and Governmental Change Enabled through Information Technology.</title><venue>VLDB</venue><pages>651-654</pages><year>2000</year><type>Conference and Workshop Papers</type><access>open</access><key>conf/vldb/RamamrithamABEGP00</key><ee>http://www.vldb.org/conf/2000/P651.pdf</ee><url>https://dblp.org/rec/conf/vldb/RamamrithamABEGP00</url></info>
<url>URL#6945817</url>
</hit>
<hit score="1" id="6945818">
<info><authors><author pid="r/KRamasamy">Karthikeyan Ramasamy</author><author pid="p/JMPatel">Jignesh M. Patel</author><author pid="n/JeffreyFNaughton">Jeffrey F. Naughton</author><author pid="09/2901">Raghav Kaushik</author></authors><title>Set Containment Joins: The Good, The Bad and The Ugly.</title><venue>VLDB</venue><pages>351-362</pages><year>2000</year><type>Conference and Workshop Papers</type><access>open</access><key>conf/vldb/RamasamyPNK00</key><ee>http://www.vldb.org/conf/2000/P351.pdf</ee><url>https://dblp.org/rec/conf/vldb/RamasamyPNK00</url></info>
<url>URL#6945818</url>
</hit>
<hit score="1" id="6945819">
<info><authors><author pid="85/6371">Sridhar Ramaswamy</author></authors><title>E.piphany Epicenter Technology Overview.</title><venue>VLDB</venue><pages>723</pages><year>2000</year><type>Conference and Workshop Papers</type><access>open</access><key>conf/vldb/Ramaswamy00</key><ee>http://www.vldb.org/conf/2000/P723.pdf</ee><url>https://dblp.org/rec/conf/vldb/Ramaswamy00</url></info>
<url>URL#6945819</url>
</hit>
<hit score="1" id="6945820">
<info><authors><author pid="99/2484">Frank Ramsak</author><author pid="m/VMarkl">Volker Markl</author><author pid="57/3333">Robert Fenk</author><author pid="22/2441">Martin Zirkel</author><author pid="40/322">Klaus Elhardt</author><author pid="b/RudolfBayer">Rudolf Bayer</author></authors><title>Integrating the UB-Tree into a Database System Kernel.</title><venue>VLDB</venue><pages>263-272</pages><year>2000</year><type>Conference and Workshop Papers</type><access>open</access><key>conf/vldb/RamsakMFZEB00</key><ee>http://www.vldb.org/conf/2000/P263.pdf</ee><url>https://dblp.org/rec/conf/vldb/RamsakMFZEB00</url></info>
<url>URL#6945820</url>
</hit>
<hit score="1" id="6945821">
<info><authors><author pid="r/NaphtaliRishe">Naphtali Rishe</author><author pid="98/4381">Jun Yuan</author><author pid="99/4201">Rukshan Athauda</author><author pid="c/ShuChingChen">Shu-Ching Chen</author><author pid="47/6186">Xiaoling Lu</author><author pid="91/172">Xiaobin Ma</author><author pid="36/776">Alexander Vaschillo</author><author pid="41/3115">Artyom Shaposhnikov</author><author pid="22/746">Dmitry Vasilevsky</author></authors><title>Semantic Access: Semantic Interface for Querying Databases.</title><venue>VLDB</venue><pages>591-594</pages><year>2000</year><type>Conference and Workshop Papers</type><access>open</access><key>conf/vldb/RisheYACLMVSV00</key><ee>http://www.vldb.org/conf/2000/P591.pdf</ee><url>https://dblp.org/rec/conf/vldb/RisheYACLMVSV00</url></info>
<url>URL#6945821</url>
</hit>
<hit score="1" id="6945822">
<info><authors><author pid="s/YasushiSakurai">Yasushi Sakurai</author><author pid="y/MasatoshiYoshikawa">Masatoshi Yoshikawa</author><author pid="97/4305">Shunsuke Uemura</author><author pid="22/1995">Haruhiko Kojima</author></authors><title>The A-tree: An Index Structure for High-Dimensional Spaces Using Relative Approximation.</title><venue>VLDB</venue><pages>516-526</pages><year>2000</year><type>Conference and Workshop Papers</type><access>open</access><key>conf/vldb/SakuraiYUK00</key><ee>http://www.vldb.org/conf/2000/P516.pdf</ee><url>https://dblp.org/rec/conf/vldb/SakuraiYUK00</url></info>
<url>URL#6945822</url>
</hit>
<hit score="1" id="6945823">
<info><authors><author pid="s/SunitaSarawagi">Sunita Sarawagi</author></authors><title>User-Adaptive Exploration of Multidimensional Data.</title><venue>VLDB</venue><pages>307-316</pages><year>2000</year><type>Conference and Workshop Papers</type><access>open</access><key>conf/vldb/Sarawagi00</key><ee>http://www.vldb.org/conf/2000/P307.pdf</ee><url>https://dblp.org/rec/conf/vldb/Sarawagi00</url></info>
<url>URL#6945823</url>
</hit>
<hit score="1" id="6945824">
<info><authors><author pid="86/144">Elvira Schaefer</author><author pid="05/431">Jan-Dirk Becker</author><author pid="10/1830">Andreas Boehmer</author><author pid="j/MatthiasJarke">Matthias Jarke</author></authors><title>Controlling Data Warehouses with Knowledge Networks.</title><venue>VLDB</venue><pages>715-718</pages><year>2000</year><type>Conference and Workshop Papers</type><access>open</access><key>conf/vldb/SchaeferBBJ00</key><ee>http://www.vldb.org/conf/2000/P715.pdf</ee><url>https://dblp.org/rec/conf/vldb/SchaeferBBJ00</url></info>
<url>URL#6945824</url>
</hit>
<hit score="1" id="6945825">
<info><authors><author pid="s/HansJorgSchek">Hans-Jörg Schek</author></authors><title>Panel: Future Directions of Database Research - The VLDB Broadening Strategy, Part 1.</title><venue>VLDB</venue><pages>663-664</pages><year>2000</year><type>Conference and Workshop Papers</type><access>open</access><key>conf/vldb/Schek00</key><ee>http://www.vldb.org/conf/2000/P663.pdf</ee><url>https://dblp.org/rec/conf/vldb/Schek00</url></info>
<url>URL#6945825</url>
</hit>
<hit score="1" id="6945826">
<info><authors><author pid="90/2469">John L. Schnase</author></authors><title>Research Directions in Biodiversity Informatics</title><venue>VLDB</venue><pages>697-700</pages><year>2000</year><type>Conference and Workshop Papers</type><access>open</access><key>conf/vldb/Schnase00</key><ee>http://www.vldb.org/conf/2000/P697.pdf</ee><url>https://dblp.org/rec/conf/vldb/Schnase00</url></info>
<url>URL#6945826</url>
</hit>
<hit score="1" id="6945827">
<info><authors><author pid="s/CyrusShahabi">Cyrus Shahabi</author><author pid="51/4632">Adil Faisal</author><author pid="34/508">Farnoush Banaei Kashani</author><author pid="28/6364">Jabed Faruque</author></authors><title>INSITE: A Tool for Interpreting Users? Interaction with a Web Space.</title><venue>VLDB</venue><pages>635-638</pages><year>2000</year><type>Conference and Workshop Papers</type><access>open</access><key>conf/vldb/ShahabiFKF00</key><ee>http://www.vldb.org/conf/2000/P635.pdf</ee><url>https://dblp.org/rec/conf/vldb/ShahabiFKF00</url></info>
<url>URL#6945827</url>
</hit>
<hit score="1" id="6945828">
<info><authors><author pid="s/JShanmugasundaram">Jayavel Shanmugasundaram</author><author pid="03/6706">Eugene J. Shekita</author><author pid="09/6129">Rimon Barr</author><author pid="31/3455">Michael J. Carey 0001</author><author pid="l/BruceGLindsay1">Bruce G. Lindsay 0001</author><author pid="p/HamidPirahesh">Hamid Pirahesh</author><author pid="76/3381">Berthold Reinwald</author></authors><title>Efficiently Publishing Relational Data as XML Documents.</title><venue>VLDB</venue><pages>65-76</pages><year>2000</year><type>Conference and Workshop Papers</type><access>open</access><key>conf/vldb/ShanmugasundaramSBCLPR00</key><ee>http://www.vldb.org/conf/2000/P065.pdf</ee><url>https://dblp.org/rec/conf/vldb/ShanmugasundaramSBCLPR00</url></info>
<url>URL#6945828</url>
</hit>
<hit score="1" id="6945829">
<info><authors><author pid="67/5256">Jagannathan Srinivasan</author><author pid="40/4423">Souripriya Das</author><author pid="35/6495">Chuck Freiwald</author><author pid="28/4369">Eugene Inseok Chong</author><author pid="85/6891">Mahesh Jagannath</author><author pid="28/3700">Aravind Yalamanchi</author><author pid="05/4051">Ramkumar Krishnan</author><author pid="95/1890-5">Anh-Tuan Tran 0005</author><author pid="36/688">Samuel DeFazio</author><author pid="21/5617">Jayanta Banerjee</author></authors><title>Oracle8i Index-Organized Table and Its Application to New Domains.</title><venue>VLDB</venue><pages>285-296</pages><year>2000</year><type>Conference and Workshop Papers</type><access>open</access><key>conf/vldb/SrinivasanDFCJYKTDB00</key><ee>http://www.vldb.org/conf/2000/P285.pdf</ee><url>https://dblp.org/rec/conf/vldb/SrinivasanDFCJYKTDB00</url></info>
<url>URL#6945829</url>
</hit>
<hit score="1" id="6945830">
<info><authors><author pid="38/4461">Thomas Stöhr</author><author pid="48/3921">Holger Märtens</author><author pid="r/ERahm">Erhard Rahm</author></authors><title>Multi-Dimensional Database Allocation for Parallel Data Warehouses.</title><venue>VLDB</venue><pages>273-284</pages><year>2000</year><type>Conference and Workshop Papers</type><access>open</access><key>conf/vldb/StohrMR00</key><ee>http://www.vldb.org/conf/2000/P273.pdf</ee><url>https://dblp.org/rec/conf/vldb/StohrMR00</url></info>
<url>URL#6945830</url>
</hit>
<hit score="1" id="6945831">
<info><authors><author pid="91/3825">Richard Taylor</author></authors><title>Concurrency in the Data Warehouse.</title><venue>VLDB</venue><pages>724-727</pages><year>2000</year><type>Conference and Workshop Papers</type><access>open</access><key>conf/vldb/Taylor00</key><ee>http://www.vldb.org/conf/2000/P724.pdf</ee><url>https://dblp.org/rec/conf/vldb/Taylor00</url></info>
<url>URL#6945831</url>
</hit>
<hit score="1" id="6945832">
<info><title>High-Performance and Scalability through Application Tier,In-Memory Data Management.</title><venue>VLDB</venue><pages>677-680</pages><year>2000</year><type>Conference and Workshop Papers</type><access>open</access><key>conf/vldb/Team00</key><ee>http://www.vldb.org/conf/2000/P677.pdf</ee><url>https://dblp.org/rec/conf/vldb/Team00</url></info>
<url>URL#6945832</url>
</hit>
<hit score="1" id="6945833">
<info><authors><author pid="t/ShalomTsur">Shalom Tsur</author></authors><title>Data Mining in the Bioinformatics Domain.</title><venue>VLDB</venue><pages>711-714</pages><year>2000</year><type>Conference and Workshop Papers</type><access>open</access><key>conf/vldb/Tsur00</key><ee>http://www.vldb.org/conf/2000/P711.pdf</ee><url>https://dblp.org/rec/conf/vldb/Tsur00</url></info>
<url>URL#6945833</url>
</hit>
<hit score="1" id="6945834">
<info><authors><author pid="w/KeWang">Ke Wang 0001</author><author pid="16/3418">Yu He</author><author pid="h/JiaweiHan">Jiawei Han 0001</author></authors><title>Mining Frequent Itemsets Using Support Constraints.</title><venue>VLDB</venue><pages>43-52</pages><year>2000</year><type>Conference and Workshop Papers</type><access>open</access><key>conf/vldb/WangHH00</key><ee>http://www.vldb.org/conf/2000/P043.pdf</ee><url>https://dblp.org/rec/conf/vldb/WangHH00</url></info>
<url>URL#6945834</url>
</hit>
<hit score="1" id="6945835">
<info><authors><author pid="w/HaixunWang">Haixun Wang</author><author pid="z/CZaniolo">Carlo Zaniolo</author></authors><title>Using SQL to Build New Aggregates and Extenders for Object- Relational Systems.</title><venue>VLDB</venue><pages>166-175</pages><year>2000</year><type>Conference and Workshop Papers</type><access>open</access><key>conf/vldb/WangZ00</key><ee>http://www.vldb.org/conf/2000/P166.pdf</ee><url>https://dblp.org/rec/conf/vldb/WangZ00</url></info>
<url>URL#6945835</url>
</hit>
<hit score="1" id="6945836">
<info><authors><author pid="84/5333">Leejay Wu</author><author pid="f/CFaloutsos">Christos Faloutsos</author><author pid="s/KatiaPSycara">Katia P. Sycara</author><author pid="p/TerryRPayne">Terry R. Payne</author></authors><title>FALCON: Feedback Adaptive Loop for Content-Based Retrieval.</title><venue>VLDB</venue><pages>297-306</pages><year>2000</year><type>Conference and Workshop Papers</type><access>open</access><key>conf/vldb/WuFSP00</key><ee>http://www.vldb.org/conf/2000/P297.pdf</ee><url>https://dblp.org/rec/conf/vldb/WuFSP00</url></info>
<url>URL#6945836</url>
</hit>
<hit score="1" id="6945837">
<info><title>Ordering Information, Conference Organizers, Program Committees, Additional Reviewers, Additional Demonstrations Reviewers, Sponsors, VLDB Endowment, Preface, Foreword.</title><venue>VLDB</venue><year>2000</year><type>Conference and Workshop Papers</type><access>open</access><key>conf/vldb/X00</key><ee>http://www.vldb.org/conf/2000/frontmatter.pdf</ee><url>https://dblp.org/rec/conf/vldb/X00</url></info>
<url>URL#6945837</url>
</hit>
<hit score="1" id="6945838">
<info><title>Author Index.</title><venue>VLDB</venue><year>2000</year><type>Conference and Workshop Papers</type><access>open</access><key>conf/vldb/X00a</key><ee>http://www.vldb.org/conf/2000/aindex.pdf</ee><url>https://dblp.org/rec/conf/vldb/X00a</url></info>
<url>URL#6945838</url>
</hit>
<hit score="1" id="6945839">
<info><authors><author pid="26/3600">Khaled Yagoub</author><author pid="70/3007">Daniela Florescu</author><author pid="i/ValerieIssarny">Valérie Issarny</author><author pid="v/PatrickValduriez">Patrick Valduriez</author></authors><title>Caching Strategies for Data-Intensive Web Sites.</title><venue>VLDB</venue><pages>188-199</pages><year>2000</year><type>Conference and Workshop Papers</type><access>open</access><key>conf/vldb/YagoubFIV00</key><ee>http://www.vldb.org/conf/2000/P188.pdf</ee><url>https://dblp.org/rec/conf/vldb/YagoubFIV00</url></info>
<url>URL#6945839</url>
</hit>
<hit score="1" id="6945840">
<info><authors><author pid="26/3600">Khaled Yagoub</author><author pid="70/3007">Daniela Florescu</author><author pid="i/ValerieIssarny">Valérie Issarny</author><author pid="v/PatrickValduriez">Patrick Valduriez</author></authors><title>Building and Customizing Data-Intensive Web Sites Using Weave.</title><venue>VLDB</venue><year>2000</year><type>Conference and Workshop Papers</type><access>unavailable</access><key>conf/vldb/YagoubFIV00a</key><url>https://dblp.org/rec/conf/vldb/YagoubFIV00a</url></info>
<url>URL#6945840</url>
</hit>
<hit score="1" id="6945841">
<info><authors><author pid="12/4952">Byoung-Kee Yi</author><author pid="f/CFaloutsos">Christos Faloutsos</author></authors><title>Fast Time Sequence Indexing for Arbitrary Lp Norms.</title><venue>VLDB</venue><pages>385-394</pages><year>2000</year><type>Conference and Workshop Papers</type><access>open</access><key>conf/vldb/YiF00</key><ee>http://www.vldb.org/conf/2000/P385.pdf</ee><url>https://dblp.org/rec/conf/vldb/YiF00</url></info>
<url>URL#6945841</url>
</hit>
<hit score="1" id="6945842">
<info><authors><author pid="69/1249">Haifeng Yu</author><author pid="v/AminVahdat">Amin Vahdat</author></authors><title>Efficient Numerical Error Bounding for Replicated Network Services.</title><venue>VLDB</venue><pages>123-133</pages><year>2000</year><type>Conference and Workshop Papers</type><access>open</access><key>conf/vldb/YuV00</key><ee>http://www.vldb.org/conf/2000/P123.pdf</ee><url>https://dblp.org/rec/conf/vldb/YuV00</url></info>
<url>URL#6945842</url>
</hit>
<hit score="1" id="6949117">
<info><authors><author pid="a/AmrElAbbadi">Amr El Abbadi</author><author pid="95/3763">Michael L. Brodie</author><author pid="c/SChakravarthy">Sharma Chakravarthy</author><author pid="76/2198">Umeshwar Dayal</author><author pid="93/6123">Nabil Kamel</author><author pid="19/4663">Gunter Schlageter</author><author pid="w/KyuYoungWhang">Kyu-Young Whang</author></authors><title>VLDB 2000, Proceedings of 26th International Conference on Very Large Data Bases, September 10-14, 2000, Cairo, Egypt</title><publisher>Morgan Kaufmann</publisher><year>2000</year><type>Editorship</type><access>unavailable</access><key>conf/vldb/2000</key><url>https://dblp.org/rec/conf/vldb/2000</url></info>
<url>URL#6949117</url>
</hit>
</hits>
</result>
